stopuhr/__init__.py
stopuhr/chrono.py
stopuhr/funkuhr.py
stopuhr/stopuhr.py
stopuhr-0.0.10.dist-info/METADATA
stopuhr-0.0.10.dist-info/WHEEL
stopuhr-0.0.10.dist-info/licenses/LICENSE
stopuhr-0.0.10.dist-info/RECORD
