Metadata-Version: 2.4
Name: stopuhr
Version: 0.0.10
Summary: A simple tool for measuring durations in Python.
Project-URL: Documentation, https://relativityhd.github.io/stopuhr/latest/
Project-URL: Repository, https://github.com/relativityhd/stopuhr
Project-URL: Issues, https://github.com/relativityhd/stopuhr/issues
Author-email: Tobais Hölzer <tobiashoelzer@hotmail.com>
License-Expression: MIT
License-File: LICENSE
Classifier: Operating System :: OS Independent
Classifier: Programming Language :: Python :: 3
Requires-Python: >=3.11
Provides-Extra: export
Requires-Dist: pandas>=2.2.3; extra == 'export'
